Workbook

Sheet Отчет
A1: Отчет о работе в апреле 2026
A2: Источник: Финансист_ВС. (1).xlsx, лист Апрель 26
A4: Клиент | B4: Суть работ | C4: Результат | D4: Вывод | E4: Кол-во записей | F4: Часы | G4: Стоимость
A5: Арк | B5: Подготовка ОДДС за март по Арктике. | C5: Отчет за март собран. | D5: Разовая отчетная работа, результат закрыт. | E5: =COUNTIF('Данные'!$C:$C,A5) | F5: =SUMIF('Данные'!$C:$C,A5,'Данные'!$E:$E) | G5: =SUMIF('Данные'!$C:$C,A5,'Данные'!$F:$F)
A6: Атт | B6: Сбор факта за февраль-март 2026, разнесение по статьям ДДС, заполнение формы и проверка ошибок. | C6: ДДС за февраль-март собран, классифицирован и проверен. | D6: Данные приведены к управленческому виду; остаточный риск - ошибки первичных данных. | E6: =COUNTIF('Данные'!$C:$C,A6) | F6: =SUMIF('Данные'!$C:$C,A6,'Данные'!$E:$E) | G6: =SUMIF('Данные'!$C:$C,A6,'Данные'!$F:$F)
A7: ИП С О.Е. | B7: Сбор данных из 1С для отчета за 2025 год, заполнение БДР за ноябрь-декабрь 2025, проверка остатков с июня 2025. | C7: БДР за ноябрь-декабрь подготовлен; по остаткам выявлено расхождение с программой и выполнена корректировка. | D7: Отчетность продвинута, но остатки требуют дополнительной сверки с учетной базой. | E7: =COUNTIF('Данные'!$C:$C,A7) | F7: =SUMIF('Данные'!$C:$C,A7,'Данные'!$E:$E) | G7: =SUMIF('Данные'!$C:$C,A7,'Данные'!$F:$F)
A8: ИП С С.П. | B8: Подготовка ДДС за март 2026, свод по статьям, проверка прошлых периодов, работа с БДР за ноябрь-декабрь 2025. | C8: ДДС за март и БДР за ноябрь-декабрь собраны и проверены по базам. | D8: Основные управленческие формы собраны; база для анализа периода готова. | E8: =COUNTIF('Данные'!$C:$C,A8) | F8: =SUMIF('Данные'!$C:$C,A8,'Данные'!$E:$E) | G8: =SUMIF('Данные'!$C:$C,A8,'Данные'!$F:$F)
A9: ИП С С.П. (новый продукт) | B9: Анализ разговора с клиентом, подготовка план-шаблона внедрения, рабочий созвон. | C9: Сформирован стартовый план внедрения нового продукта. | D9: Клиент переведен из обсуждения в этап планирования внедрения. | E9: =COUNTIF('Данные'!$C:$C,A9) | F9: =SUMIF('Данные'!$C:$C,A9,'Данные'!$E:$E) | G9: =SUMIF('Данные'!$C:$C,A9,'Данные'!$F:$F)
A10: Рем | B10: Ведение и настройка платежного календаря, реестра платежей, договоров и займов; сверки с банком и Диадоком; регламент работы; разбор налогов за 1 квартал 2026; ответы по требованиям ИФНС; пояснения собственнику. | C10: Платежный календарь и реестры поддерживались в рабочем состоянии, данные по договорам, займам и оплатам обновлялись, регламент подготовлен и согласовывался, налоговые вопросы и требования разобраны. | D10: Ключевой объем месяца: операционное сопровождение казначейства плюс налоговые разборы. Есть риски по качеству входящих данных и реквизитам оплат. | E10: =COUNTIF('Данные'!$C:$C,A10) | F10: =SUMIF('Данные'!$C:$C,A10,'Данные'!$E:$E) | G10: =SUMIF('Данные'!$C:$C,A10,'Данные'!$F:$F)
A11: УФ | B11: Разработка и запуск нового продукта: переговоры с потенциальными клиентами, презентации и КП, шаблоны и чек-листы; по УС - ДДС-справочник, платежный календарь, факт апреля, банковские выписки и наличные; по УРС - подготовка к внедрению, доступы, изучение СБИС и таблиц. | C11: Подготовлена база для внедрения нового продукта; по УС создан и наполнен платежный календарь с ДДС-структурой; по УРС собраны вводные и вопросы для продолжения работ. | D11: Внутренние работы не тарифицировались, но сформировали основу продукта и пилотные материалы для клиентов. | E11: =COUNTIF('Данные'!$C:$C,A11) | F11: =SUMIF('Данные'!$C:$C,A11,'Данные'!$E:$E) | G11: =SUMIF('Данные'!$C:$C,A11,'Данные'!$F:$F)
A12: Итого | E12: =SUM(E5:E11) | F12: =SUM(F5:F11) | G12: =SUM(G5:G11)
A14: Проверка данных
A15: Всего строк исходных данных: формула на листе показывает количество записей по клиентам.
A16: Обнаружена дата 24.04.0202: похоже на ошибку ввода, требуется проверка в исходном табеле.
A17: Есть строки с нулевыми часами по УФ: они оставлены в данных, так как присутствуют в исходном файле.
A18: По УФ стоимость равна 0,00: в исходном файле стоит формула с нулевой стоимостью для внутреннего контрагента.

Sheet Данные
A1: Дата | B1: № п/п | C1: Контрагент | D1: Наименование работ | E1: Количество часов | F1: Стоимость
A2: 01.04.2026 | B2: 1 | C2: УФ | D2: новый продукт, определение клиентов, | E2: 0.5 | F2: 0
A3: 01.04.2026 | B3: 2 | C3: УФ | D3: созвон с Татьяна ДТД УРС, АЛТР- проверка заполнения сделки , как удобнее связываться и чем компания занимаеться | E3: 0.5 | F3: 0
A4: 01.04.2026 | B4: 3 | C4: УФ | D4: Созвон с собствеником Тарасом П АЛТР- не понятен продукт , хочется наглядно, ведет платежный календарь на гугл таблицах , в налогах разбирается лучше бухгалтерии | E4: 0.3 | F4: 0
A5: 01.04.2026 | B5: 4 | C5: УФ | D5: сбор и отправка документов на корпоротивную почту, презентация и пример платежного календаря | E5: 0.7 | F5: 0
A6: 01.04.2026 | B6: 5 | C6: УФ | D6: выставление счета и пояснение для ИП Неп необходимость оплатить счет за март, так как банковские выписка были выгруженные только 2 марта в первый рабочий день, отчет за февраль бы сформирован только 3 марта и отправлен Литвиновой Юлии, которая отказалась с нами сотрудничать в марте. | E6: 0.58333333 | F6: 0
A7: 01.04.2026 | B7: 6 | C7: УФ | D7: не дозвонилась до Фад, написала в чате ТД УРС- проверка как заполнена сделка , какая система налогообложения | E7: 0.28333333 | F7: 0
A8: 01.04.2026 | B8: 7 | C8: УФ | D8: АЛТР зантересовала только предложение по оптимизации налогов | E8: 0.25 | F8: 0
A9: 01.04.2026 | B9: 8 | C9: УФ | D9: разьяснение ИП Неп- что оплата за февраль не могла быть включена в февраль, так как работы были сделаны фактически в марте, счет выставлен по факту. Расчет сумм предварительно не возможен, поскольку фактические работы за февраль были оплачены не в полном обьеме. | E9: 0.25 | F9: 0
A10: 01.04.2026 | B10: 9 | C10: УФ | D10: Пыталась найти базы двух компаний, выясняла с бухгалтерией | E10: 0.5 | F10: 0
A11: 01.04.2026 | B11: 10 | C11: УФ | D11: Ф-тэк выясняю кто бухгалтер | E11: 0.25 | F11: 0
A12: 01.04.2026 | B12: 11 | C12: УФ | D12: Созвон с Мирошниченко Людмилой | E12: 1 | F12: 0
A13: 02.04.2026 | B13: 12 | C13: УФ | D13: Ф-тэк, сбор информации по клиенту, созвон- коротко кто я и что я хочу. Подготовка письма дляЛитвиновских Алексея с описанием нашего нового продукта , приложила презентпцию исправленную и образец платежного календаря. | E13: 1.5 | F13: 0
... A174: 30.04.2026 | B174: 170 | C174: Рем | D174: Платежный календарь с Ириной , реквизиты и счета | E174: 0.83333333 | F174: 1666.6667
