Workbook

Sheet Ops
A1: Новые строки добавляйте только под таблицей. Даты вводите в формате даты Excel.
A3: Дата | B3: Операция | C3: Статья | D3: Поступления | E3: Списания | F3: Чистый поток | G3: Год | H3: Месяц | I3: Квартал
A4: 01.04.2026 | B4: Поступление | C4: Оплата от покупателя | D4: 31440 | F4: =D4-E4 -> 31440 | G4: =YEAR(A4) -> 2026 | H4: =MONTH(A4) -> 4 | I4: =ROUNDUP(H4/3,0) -> 2
A5: 01.04.2026 | B5: Поступление | C5: Оплата от покупателя | D5: 13622 | F5: =D5-E5 -> 13622 | G5: =YEAR(A5) -> 2026 | H5: =MONTH(A5) -> 4 | I5: =ROUNDUP(H5/3,0) -> 2
A6: 01.04.2026 | B6: Поступление | C6: Оплата от покупателя | D6: 13795 | F6: =D6-E6 -> 13795 | G6: =YEAR(A6) -> 2026 | H6: =MONTH(A6) -> 4 | I6: =ROUNDUP(H6/3,0) -> 2
A7: 01.04.2026 | B7: Поступление | C7: Оплата от покупателя | D7: 136955 | F7: =D7-E7 -> 136955 | G7: =YEAR(A7) -> 2026 | H7: =MONTH(A7) -> 4 | I7: =ROUNDUP(H7/3,0) -> 2
A8: 01.04.2026 | B8: Поступление | C8: перевод со счета на счет | D8: 4716 | F8: =D8-E8 -> 4716 | G8: =YEAR(A8) -> 2026 | H8: =MONTH(A8) -> 4 | I8: =ROUNDUP(H8/3,0) -> 2
A9: 01.04.2026 | B9: Поступление | C9: перевод со счета на счет | D9: 2043.3 | F9: =D9-E9 -> 2043.3 | G9: =YEAR(A9) -> 2026 | H9: =MONTH(A9) -> 4 | I9: =ROUNDUP(H9/3,0) -> 2
A10: 01.04.2026 | B10: Поступление | C10: перевод со счета на счет | D10: 2069.25 | F10: =D10-E10 -> 2069.25 | G10: =YEAR(A10) -> 2026 | H10: =MONTH(A10) -> 4 | I10: =ROUNDUP(H10/3,0) -> 2
A11: 01.04.2026 | B11: Поступление | C11: перевод со счета на счет | D11: 20543.25 | F11: =D11-E11 -> 20543.25 | G11: =YEAR(A11) -> 2026 | H11: =MONTH(A11) -> 4 | I11: =ROUNDUP(H11/3,0) -> 2
A12: 01.04.2026 | B12: Поступление | C12: Эквайринг | D12: 71636.58 | F12: =D12-E12 -> 71636.58 | G12: =YEAR(A12) -> 2026 | H12: =MONTH(A12) -> 4 | I12: =ROUNDUP(H12/3,0) -> 2
A13: 01.04.2026 | B13: Списание | C13: перевод со счета на счет | E13: 4716 | F13: =D13-E13 -> -4716 | G13: =YEAR(A13) -> 2026 | H13: =MONTH(A13) -> 4 | I13: =ROUNDUP(H13/3,0) -> 2
A14: 01.04.2026 | B14: Списание | C14: перевод со счета на счет | E14: 2043.3 | F14: =D14-E14 -> -2043.3 | G14: =YEAR(A14) -> 2026 | H14: =MONTH(A14) -> 4 | I14: =ROUNDUP(H14/3,0) -> 2
A15: 01.04.2026 | B15: Списание | C15: перевод со счета на счет | E15: 2069.25 | F15: =D15-E15 -> -2069.25 | G15: =YEAR(A15) -> 2026 | H15: =MONTH(A15) -> 4 | I15: =ROUNDUP(H15/3,0) -> 2
A16: 01.04.2026 | B16: Списание | C16: перевод со счета на счет | E16: 20543.25 | F16: =D16-E16 -> -20543.25 | G16: =YEAR(A16) -> 2026 | H16: =MONTH(A16) -> 4 | I16: =ROUNDUP(H16/3,0) -> 2
A17: 01.04.2026 | B17: Списание | C17: Коммунальные услуги | E17: 481.78 | F17: =D17-E17 -> -481.78 | G17: =YEAR(A17) -> 2026 | H17: =MONTH(A17) -> 4 | I17: =ROUNDUP(H17/3,0) -> 2
A18: 01.04.2026 | B18: Списание | C18: транспортно-экспедиционные услуги | E18: 912.2 | F18: =D18-E18 -> -912.2 | G18: =YEAR(A18) -> 2026 | H18: =MONTH(A18) -> 4 | I18: =ROUNDUP(H18/3,0) -> 2
A19: 01.04.2026 | B19: Списание | C19: Возврат кредита банку | E19: 117530.76 | F19: =D19-E19 -> -117530.76 | G19: =YEAR(A19) -> 2026 | H19: =MONTH(A19) -> 4 | I19: =ROUNDUP(H19/3,0) -> 2
A20: 02.04.2026 | B20: Поступление | C20: Оплата от покупателя | D20: 94450 | F20: =D20-E20 -> 94450 | G20: =YEAR(A20) -> 2026 | H20: =MONTH(A20) -> 4 | I20: =ROUNDUP(H20/3,0) -> 2
A21: 02.04.2026 | B21: Поступление | C21: Оплата от покупателя | D21: 53741.5 | F21: =D21-E21 -> 53741.5 | G21: =YEAR(A21) -> 2026 | H21: =MONTH(A21) -> 4 | I21: =ROUNDUP(H21/3,0) -> 2
A22: 02.04.2026 | B22: Поступление | C22: перевод со счета на счет | D22: 14167.5 | F22: =D22-E22 -> 14167.5 | G22: =YEAR(A22) -> 2026 | H22: =MONTH(A22) -> 4 | I22: =ROUNDUP(H22/3,0) -> 2
A23: 02.04.2026 | B23: Поступление | C23: перевод со счета на счет | D23: 8061.22 | F23: =D23-E23 -> 8061.22 | G23: =YEAR(A23) -> 2026 | H23: =MONTH(A23) -> 4 | I23: =ROUNDUP(H23/3,0) -> 2
A24: 02.04.2026 | B24: Поступление | C24: Эквайринг | D24: 5120.48 | F24: =D24-E24 -> 5120.48 | G24: =YEAR(A24) -> 2026 | H24: =MONTH(A24) -> 4 | I24: =ROUNDUP(H24/3,0) -> 2
A25: 02.04.2026 | B25: Списание | C25: перевод со счета на счет | E25: 14167.5 | F25: =D25-E25 -> -14167.5 | G25: =YEAR(A25) -> 2026 | H25: =MONTH(A25) -> 4 | I25: =ROUNDUP(H25/3,0) -> 2
A26: 02.04.2026 | B26: Списание | C26: Программное обеспечение, Каталоги, Лицензии | E26: 18900 | F26: =D26-E26 -> -18900 | G26: =YEAR(A26) -> 2026 | H26: =MONTH(A26) -> 4 | I26: =ROUNDUP(H26/3,0) -> 2
A27: 02.04.2026 | B27: Списание | C27: перевод со счета на счет | E27: 8061.22 | F27: =D27-E27 -> -8061.22 | G27: =YEAR(A27) -> 2026 | H27: =MONTH(A27) -> 4 | I27: =ROUNDUP(H27/3,0) -> 2
A28: 02.04.2026 | B28: Списание | C28: Услуги связи | E28: 3173.14 | F28: =D28-E28 -> -3173.14 | G28: =YEAR(A28) -> 2026 | H28: =MONTH(A28) -> 4 | I28: =ROUNDUP(H28/3,0) -> 2
A29: 02.04.2026 | B29: Списание | C29: Коммунальные услуги | E29: 2407.68 | F29: =D29-E29 -> -2407.68 | G29: =YEAR(A29) -> 2026 | H29: =MONTH(A29) -> 4 | I29: =ROUNDUP(H29/3,0) -> 2
A30: 02.04.2026 | B30: Списание | C30: Коммунальные услуги | E30: 6879.7 | F30: =D30-E30 -> -6879.7 | G30: =YEAR(A30) -> 2026 | H30: =MONTH(A30) -> 4 | I30: =ROUNDUP(H30/3,0) -> 2
A31: 02.04.2026 | B31: Списание | C31: Подотчет | E31: 650 | F31: =D31-E31 -> -650 | G31: =YEAR(A31) -> 2026 | H31: =MONTH(A31) -> 4 | I31: =ROUNDUP(H31/3,0) -> 2
A32: 03.04.2026 | B32: Поступление | C32: Оплата от покупателя | D32: 14112 | F32: =D32-E32 -> 14112 | G32: =YEAR(A32) -> 2026 | H32: =MONTH(A32) -> 4 | I32: =ROUNDUP(H32/3,0) -> 2
A33: 03.04.2026 | B33: Поступление | C33: перевод со счета на счет | D33: 2116.8 | F33: =D33-E33 -> 2116.8 | G33: =YEAR(A33) -> 2026 | H33: =MONTH(A33) -> 4 | I33: =ROUNDUP(H33/3,0) -> 2
A34: 03.04.2026 | B34: Поступление | C34: Эквайринг | D34: 2163.92 | F34: =D34-E34 -> 2163.92 | G34: =YEAR(A34) -> 2026 | H34: =MONTH(A34) -> 4 | I34: =ROUNDUP(H34/3,0) -> 2
A35: 03.04.2026 | B35: Списание | C35: перевод со счета на счет | E35: 2116.8 | F35: =D35-E35 -> -2116.8 | G35: =YEAR(A35) -> 2026 | H35: =MONTH(A35) -> 4 | I35: =ROUNDUP(H35/3,0) -> 2
A36: 03.04.2026 | B36: Списание | C36: Коммунальные услуги | E36: 963.56 | F36: =D36-E36 -> -963.56 | G36: =YEAR(A36) -> 2026 | H36: =MONTH(A36) -> 4 | I36: =ROUNDUP(H36/3,0) -> 2
A37: 03.04.2026 | B37: Списание | C37: материалы для производства | E37: 35775 | F37: =D37-E37 -> -35775 | G37: =YEAR(A37) -> 2026 | H37: =MONTH(A37) -> 4 | I37: =ROUNDUP(H37/3,0) -> 2
A38: 03.04.2026 | B38: Списание | C38: Услуги печати | E38: 40122 | F38: =D38-E38 -> -40122 | G38: =YEAR(A38) -> 2026 | H38: =MONTH(A38) -> 4 | I38: =ROUNDUP(H38/3,0) -> 2
A39: 05.04.2026 | B39: Списание | C39: Подотчет | E39: 1888.2 | F39: =D39-E39 -> -1888.2 | G39: =YEAR(A39) -> 2026 | H39: =MONTH(A39) -> 4 | I39: =ROUNDUP(H39/3,0) -> 2
A40: 06.04.2026 | B40: Поступление | C40: Оплата от покупателя | D40: 5250 | F40: =D40-E40 -> 5250 | G40: =YEAR(A40) -> 2026 | H40: =MONTH(A40) -> 4 | I40: =ROUNDUP(H40/3,0) -> 2
A41: 06.04.2026 | B41: Поступление | C41: Оплата от покупателя | D41: 8710 | F41: =D41-E41 -> 8710 | G41: =YEAR(A41) -> 2026 | H41: =MONTH(A41) -> 4 | I41: =ROUNDUP(H41/3,0) -> 2
A42: 06.04.2026 | B42: Поступление | C42: Оплата от покупателя | D42: 18335 | F42: =D42-E42 -> 18335 | G42: =YEAR(A42) -> 2026 | H42: =MONTH(A42) -> 4 | I42: =ROUNDUP(H42/3,0) -> 2
A43: 06.04.2026 | B43: Поступление | C43: Оплата от покупателя | D43: 6450 | F43: =D43-E43 -> 6450 | G43: =YEAR(A43) -> 2026 | H43: =MONTH(A43) -> 4 | I43: =ROUNDUP(H43/3,0) -> 2
A44: 06.04.2026 | B44: Поступление | C44: Оплата от покупателя | D44: 240900 | F44: =D44-E44 -> 240900 | G44: =YEAR(A44) -> 2026 | H44: =MONTH(A44) -> 4 | I44: =ROUNDUP(H44/3,0) -> 2
A45: 06.04.2026 | B45: Поступление | C45: перевод со счета на счет | D45: 787.5 | F45: =D45-E45 -> 787.5 | G45: =YEAR(A45) -> 2026 | H45: =MONTH(A45) -> 4 | I45: =ROUNDUP(H45/3,0) -> 2
A46: 06.04.2026 | B46: Поступление | C46: перевод со счета на счет | D46: 1306.5 | F46: =D46-E46 -> 1306.5 | G46: =YEAR(A46) -> 2026 | H46: =MONTH(A46) -> 4 | I46: =ROUNDUP(H46/3,0) -> 2
A47: 06.04.2026 | B47: Поступление | C47: перевод со счета на счет | D47: 2750.25 | F47: =D47-E47 -> 2750.25 | G47: =YEAR(A47) -> 2026 | H47: =MONTH(A47) -> 4 | I47: =ROUNDUP(H47/3,0) -> 2
A48: 06.04.2026 | B48: Поступление | C48: перевод со счета на счет | D48: 967.5 | F48: =D48-E48 -> 967.5 | G48: =YEAR(A48) -> 2026 | H48: =MONTH(A48) -> 4 | I48: =ROUNDUP(H48/3,0) -> 2
A49: 06.04.2026 | B49: Поступление | C49: перевод со счета на счет | D49: 36135 | F49: =D49-E49 -> 36135 | G49: =YEAR(A49) -> 2026 | H49: =MONTH(A49) -> 4 | I49: =ROUNDUP(H49/3,0) -> 2
A50: 06.04.2026 | B50: Поступление | C50: Эквайринг | D50: 6506.36 | F50: =D50-E50 -> 6506.36 | G50: =YEAR(A50) -> 2026 | H50: =MONTH(A50) -> 4 | I50: =ROUNDUP(H50/3,0) -> 2
A51: 06.04.2026 | B51: Поступление | C51: Выплата процентов по депозиту | D51: 37838.9 | F51: =D51-E51 -> 37838.9 | G51: =YEAR(A51) -> 2026 | H51: =MONTH(A51) -> 4 | I51: =ROUNDUP(H51/3,0) -> 2
A52: 06.04.2026 | B52: Поступление | C52: Депозит | D52: 4000000 | F52: =D52-E52 -> 4000000 | G52: =YEAR(A52) -> 2026 | H52: =MONTH(A52) -> 4 | I52: =ROUNDUP(H52/3,0) -> 2
A53: 06.04.2026 | B53: Списание | C53: перевод со счета на счет | E53: 787.5 | F53: =D53-E53 -> -787.5 | G53: =YEAR(A53) -> 2026 | H53: =MONTH(A53) -> 4 | I53: =ROUNDUP(H53/3,0) -> 2
A54: 06.04.2026 | B54: Списание | C54: перевод со счета на счет | E54: 1306.5 | F54: =D54-E54 -> -1306.5 | G54: =YEAR(A54) -> 2026 | H54: =MONTH(A54) -> 4 | I54: =ROUNDUP(H54/3,0) -> 2
A55: 06.04.2026 | B55: Списание | C55: Налоги на персонал | E55: 59770 | F55: =D55-E55 -> -59770 | G55: =YEAR(A55) -> 2026 | H55: =MONTH(A55) -> 4 | I55: =ROUNDUP(H55/3,0) -> 2
A56: 06.04.2026 | B56: Списание | C56: транспортно-экспедиционные услуги | E56: 3.85 | F56: =D56-E56 -> -3.85 | G56: =YEAR(A56) -> 2026 | H56: =MONTH(A56) -> 4 | I56: =ROUNDUP(H56/3,0) -> 2
A57: 06.04.2026 | B57: Списание | C57: Услуги связи | E57: 7438.71 | F57: =D57-E57 -> -7438.71 | G57: =YEAR(A57) -> 2026 | H57: =MONTH(A57) -> 4 | I57: =ROUNDUP(H57/3,0) -> 2
A58: 06.04.2026 | B58: Списание | C58: перевод со счета на счет | E58: 2750.25 | F58: =D58-E58 -> -2750.25 | G58: =YEAR(A58) -> 2026 | H58: =MONTH(A58) -> 4 | I58: =ROUNDUP(H58/3,0) -> 2
A59: 06.04.2026 | B59: Списание | C59: перевод со счета на счет | E59: 967.5 | F59: =D59-E59 -> -967.5 | G59: =YEAR(A59) -> 2026 | H59: =MONTH(A59) -> 4 | I59: =ROUNDUP(H59/3,0) -> 2
A60: 06.04.2026 | B60: Списание | C60: Коммунальные услуги | E60: 244.37 | F60: =D60-E60 -> -244.37 | G60: =YEAR(A60) -> 2026 | H60: =MONTH(A60) -> 4 | I60: =ROUNDUP(H60/3,0) -> 2
A61: 06.04.2026 | B61: Списание | C61: Товар | E61: 7740 | F61: =D61-E61 -> -7740 | G61: =YEAR(A61) -> 2026 | H61: =MONTH(A61) -> 4 | I61: =ROUNDUP(H61/3,0) -> 2
A62: 06.04.2026 | B62: Списание | C62: перевод со счета на счет | E62: 36135 | F62: =D62-E62 -> -36135 | G62: =YEAR(A62) -> 2026 | H62: =MONTH(A62) -> 4 | I62: =ROUNDUP(H62/3,0) -> 2
A63: 06.04.2026 | B63: Списание | C63: товар | E63: 61160 | F63: =D63-E63 -> -61160 | G63: =YEAR(A63) -> 2026 | H63: =MONTH(A63) -> 4 | I63: =ROUNDUP(H63/3,0) -> 2
A64: 06.04.2026 | B64: Списание | C64: Комиссия банка | E64: 2500 | F64: =D64-E64 -> -2500 | G64: =YEAR(A64) -> 2026 | H64: =MONTH(A64) -> 4 | I64: =ROUNDUP(H64/3,0) -> 2
... A68: 06.04.2026 | B68: Списание | C68: Хозрасходы, офисные расходы, мебель | E68: 2228 | F68: =D68-E68 -> -2228 | G68: =YEAR(A68) -> 2026 | H68: =MONTH(A68) -> 4 | I68: =ROUNDUP(H68/3,0) -> 2
A69: 07.04.2026 | B69: Поступление | C69: Оплата от покупателя | D69: 6600 | F69: =D69-E69 -> 6600 | G69: =YEAR(A69) -> 2026 | H69: =MONTH(A69) -> 4 | I69: =ROUNDUP(H69/3,0) -> 2
A70: 07.04.2026 | B70: Поступление | C70: Оплата от покупателя | D70: 7600 | F70: =D70-E70 -> 7600 | G70: =YEAR(A70) -> 2026 | H70: =MONTH(A70) -> 4 | I70: =ROUNDUP(H70/3,0) -> 2
A71: 07.04.2026 | B71: Поступление | C71: Оплата от покупателя | D71: 160711 | F71: =D71-E71 -> 160711 | G71: =YEAR(A71) -> 2026 | H71: =MONTH(A71) -> 4 | I71: =ROUNDUP(H71/3,0) -> 2
A72: 07.04.2026 | B72: Поступление | C72: перевод со счета на счет | D72: 990 | F72: =D72-E72 -> 990 | G72: =YEAR(A72) -> 2026 | H72: =MONTH(A72) -> 4 | I72: =ROUNDUP(H72/3,0) -> 2
A73: 07.04.2026 | B73: Поступление | C73: перевод со счета на счет | D73: 1140 | F73: =D73-E73 -> 1140 | G73: =YEAR(A73) -> 2026 | H73: =MONTH(A73) -> 4 | I73: =ROUNDUP(H73/3,0) -> 2
A74: 07.04.2026 | B74: Поступление | C74: перевод со счета на счет | D74: 24106.65 | F74: =D74-E74 -> 24106.65 | G74: =YEAR(A74) -> 2026 | H74: =MONTH(A74) -> 4 | I74: =ROUNDUP(H74/3,0) -> 2
A75: 07.04.2026 | B75: Поступление | C75: Эквайринг | D75: 4959.99 | F75: =D75-E75 -> 4959.99 | G75: =YEAR(A75) -> 2026 | H75: =MONTH(A75) -> 4 | I75: =ROUNDUP(H75/3,0) -> 2
A76: 07.04.2026 | B76: Списание | C76: Госпошлины, штрафы | E76: 1125 | F76: =D76-E76 -> -1125 | G76: =YEAR(A76) -> 2026 | H76: =MONTH(A76) -> 4 | I76: =ROUNDUP(H76/3,0) -> 2
A77: 07.04.2026 | B77: Списание | C77: перевод со счета на счет | E77: 990 | F77: =D77-E77 -> -990 | G77: =YEAR(A77) -> 2026 | H77: =MONTH(A77) -> 4 | I77: =ROUNDUP(H77/3,0) -> 2
A78: 07.04.2026 | B78: Списание | C78: материалы для производства | E78: 3500 | F78: =D78-E78 -> -3500 | G78: =YEAR(A78) -> 2026 | H78: =MONTH(A78) -> 4 | I78: =ROUNDUP(H78/3,0) -> 2
A79: 07.04.2026 | B79: Списание | C79: перевод со счета на счет | E79: 1140 | F79: =D79-E79 -> -1140 | G79: =YEAR(A79) -> 2026 | H79: =MONTH(A79) -> 4 | I79: =ROUNDUP(H79/3,0) -> 2
A80: 07.04.2026 | B80: Списание | C80: перевод со счета на счет | E80: 24106.65 | F80: =D80-E80 -> -24106.65 | G80: =YEAR(A80) -> 2026 | H80: =MONTH(A80) -> 4 | I80: =ROUNDUP(H80/3,0) -> 2
A81: 08.04.2026 | B81: Поступление | C81: Оплата от покупателя | D81: 30660 | F81: =D81-E81 -> 30660 | G81: =YEAR(A81) -> 2026 | H81: =MONTH(A81) -> 4 | I81: =ROUNDUP(H81/3,0) -> 2
A82: 08.04.2026 | B82: Поступление | C82: перевод со счета на счет | D82: 940 | F82: =D82-E82 -> 940 | G82: =YEAR(A82) -> 2026 | H82: =MONTH(A82) -> 4 | I82: =ROUNDUP(H82/3,0) -> 2
A83: 08.04.2026 | B83: Поступление | C83: Оплата от покупателя | D83: 3024 | F83: =D83-E83 -> 3024 | G83: =YEAR(A83) -> 2026 | H83: =MONTH(A83) -> 4 | I83: =ROUNDUP(H83/3,0) -> 2
A84: 08.04.2026 | B84: Поступление | C84: Оплата от покупателя | D84: 9000 | F84: =D84-E84 -> 9000 | G84: =YEAR(A84) -> 2026 | H84: =MONTH(A84) -> 4 | I84: =ROUNDUP(H84/3,0) -> 2
A85: 08.04.2026 | B85: Поступление | C85: Оплата от покупателя | D85: 162680 | F85: =D85-E85 -> 162680 | G85: =YEAR(A85) -> 2026 | H85: =MONTH(A85) -> 4 | I85: =ROUNDUP(H85/3,0) -> 2
A86: 08.04.2026 | B86: Поступление | C86: перевод со счета на счет | D86: 4599 | F86: =D86-E86 -> 4599 | G86: =YEAR(A86) -> 2026 | H86: =MONTH(A86) -> 4 | I86: =ROUNDUP(H86/3,0) -> 2
A87: 08.04.2026 | B87: Поступление | C87: перевод со счета на счет | D87: 453.6 | F87: =D87-E87 -> 453.6 | G87: =YEAR(A87) -> 2026 | H87: =MONTH(A87) -> 4 | I87: =ROUNDUP(H87/3,0) -> 2
A88: 08.04.2026 | B88: Поступление | C88: перевод со счета на счет | D88: 1350 | F88: =D88-E88 -> 1350 | G88: =YEAR(A88) -> 2026 | H88: =MONTH(A88) -> 4 | I88: =ROUNDUP(H88/3,0) -> 2
A89: 08.04.2026 | B89: Поступление | C89: перевод со счета на счет | D89: 24402 | F89: =D89-E89 -> 24402 | G89: =YEAR(A89) -> 2026 | H89: =MONTH(A89) -> 4 | I89: =ROUNDUP(H89/3,0) -> 2
A90: 08.04.2026 | B90: Поступление | C90: Эквайринг | D90: 1021.16 | F90: =D90-E90 -> 1021.16 | G90: =YEAR(A90) -> 2026 | H90: =MONTH(A90) -> 4 | I90: =ROUNDUP(H90/3,0) -> 2
A91: 08.04.2026 | B91: Списание | C91: перевод со счета на счет | E91: 4599 | F91: =D91-E91 -> -4599 | G91: =YEAR(A91) -> 2026 | H91: =MONTH(A91) -> 4 | I91: =ROUNDUP(H91/3,0) -> 2
A92: 08.04.2026 | B92: Списание | C92: перевод со счета на счет | E92: 453.6 | F92: =D92-E92 -> -453.6 | G92: =YEAR(A92) -> 2026 | H92: =MONTH(A92) -> 4 | I92: =ROUNDUP(H92/3,0) -> 2
A93: 08.04.2026 | B93: Списание | C93: товар | E93: 92167.68 | F93: =D93-E93 -> -92167.68 | G93: =YEAR(A93) -> 2026 | H93: =MONTH(A93) -> 4 | I93: =ROUNDUP(H93/3,0) -> 2
A94: 08.04.2026 | B94: Списание | C94: транспортно-экспедиционные услуги | E94: 695.4 | F94: =D94-E94 -> -695.4 | G94: =YEAR(A94) -> 2026 | H94: =MONTH(A94) -> 4 | I94: =ROUNDUP(H94/3,0) -> 2
A95: 08.04.2026 | B95: Списание | C95: услуги печати | E95: 7000 | F95: =D95-E95 -> -7000 | G95: =YEAR(A95) -> 2026 | H95: =MONTH(A95) -> 4 | I95: =ROUNDUP(H95/3,0) -> 2
A96: 08.04.2026 | B96: Списание | C96: перевод со счета на счет | E96: 1350 | F96: =D96-E96 -> -1350 | G96: =YEAR(A96) -> 2026 | H96: =MONTH(A96) -> 4 | I96: =ROUNDUP(H96/3,0) -> 2
A97: 08.04.2026 | B97: Списание | C97: перевод со счета на счет | E97: 24402 | F97: =D97-E97 -> -24402 | G97: =YEAR(A97) -> 2026 | H97: =MONTH(A97) -> 4 | I97: =ROUNDUP(H97/3,0) -> 2
A98: 08.04.2026 | B98: Списание | C98: перевод со счета на счет | E98: 940 | F98: =D98-E98 -> -940 | G98: =YEAR(A98) -> 2026 | H98: =MONTH(A98) -> 4 | I98: =ROUNDUP(H98/3,0) -> 2
A99: 09.04.2026 | B99: Поступление | C99: Оплата от покупателя | D99: 16750 | F99: =D99-E99 -> 16750 | G99: =YEAR(A99) -> 2026 | H99: =MONTH(A99) -> 4 | I99: =ROUNDUP(H99/3,0) -> 2
A100: 09.04.2026 | B100: Поступление | C100: Оплата от покупателя | D100: 41450 | F100: =D100-E100 -> 41450 | G100: =YEAR(A100) -> 2026 | H100: =MONTH(A100) -> 4 | I100: =ROUNDUP(H100/3,0) -> 2
A101: 09.04.2026 | B101: Поступление | C101: Оплата от покупателя | D101: 10745 | F101: =D101-E101 -> 10745 | G101: =YEAR(A101) -> 2026 | H101: =MONTH(A101) -> 4 | I101: =ROUNDUP(H101/3,0) -> 2
A102: 09.04.2026 | B102: Поступление | C102: Оплата от покупателя | D102: 40805 | F102: =D102-E102 -> 40805 | G102: =YEAR(A102) -> 2026 | H102: =MONTH(A102) -> 4 | I102: =ROUNDUP(H102/3,0) -> 2
A103: 09.04.2026 | B103: Поступление | C103: Оплата от покупателя | D103: 12000 | F103: =D103-E103 -> 12000 | G103: =YEAR(A103) -> 2026 | H103: =MONTH(A103) -> 4 | I103: =ROUNDUP(H103/3,0) -> 2
A104: 09.04.2026 | B104: Поступление | C104: перевод со счета на счет | D104: 2512.5 | F104: =D104-E104 -> 2512.5 | G104: =YEAR(A104) -> 2026 | H104: =MONTH(A104) -> 4 | I104: =ROUNDUP(H104/3,0) -> 2
...

Sheet Dash
A1: Дашборд ДДС
D2: Поступления | E2: Списания | F2: Чистый поток | G2: Остаток на конец
A3: Год | B3: 2026 | D3: =SUMIFS(Ops!$D:$D,Ops!$G:$G,$B$3) -> 80226191 | E3: =SUMIFS(Ops!$E:$E,Ops!$G:$G,$B$3) -> 81065607 | F3: =D3-E3 -> -839415.71 | G3: =B4+F3 -> 456872.77
A4: Начальный остаток | B4: 1296288.5 | D4: =SUMIFS(Ops!$D:$D,Ops!$G:$G,$B$3,Ops!$I:$I,1) -> 0 | E4: =SUMIFS(Ops!$E:$E,Ops!$G:$G,$B$3,Ops!$I:$I,1) -> 0 | F4: =D4-E4 -> 0 | G4: =B4+F4 -> 1296288.5
A5: Последняя дата в базе | B5: =MAX(Ops!$A:$A) -> 0 | D5: =SUMIFS(Ops!$D:$D,Ops!$G:$G,$B$3,Ops!$I:$I,2) -> 80226191 | E5: =SUMIFS(Ops!$E:$E,Ops!$G:$G,$B$3,Ops!$I:$I,2) -> 81065607 | F5: =D5-E5 -> -839415.71 | G5: =G4+F5 -> 456872.77
A6: Количество операций | B6: =COUNTIF(Ops!$A:$A,">0") -> 0 | D6: =SUMIFS(Ops!$D:$D,Ops!$G:$G,$B$3,Ops!$I:$I,3)+SUMIFS(Ops!$D:$D,Ops!$G:$G,$B$3,Ops!$I:$I,4) -> 0 | E6: =SUMIFS(Ops!$E:$E,Ops!$G:$G,$B$3,Ops!$I:$I,3)+SUMIFS(Ops!$E:$E,Ops!$G:$G,$B$3,Ops!$I:$I,4) -> 0 | F6: =D6-E6 -> 0 | G6: =G5+F6 -> 456872.77
A10: № | B10: Месяц | C10: Поступления | D10: Списания | E10: Чистый поток | F10: Остаток на конец | I10: Топ-10 статей поступлений | L10: Топ-10 статей списаний
A11: 1 | B11: Январь | C11: =SUMIFS(Ops!$D:$D,Ops!$G:$G,$B$3,Ops!$H:$H,A11) -> 0 | D11: =SUMIFS(Ops!$E:$E,Ops!$G:$G,$B$3,Ops!$H:$H,A11) -> 0 | E11: =C11-D11 -> 0 | F11: =$B$4+SUM($E$11:E11) -> 1296288.5 | I11: Статья | J11: Сумма | L11: Статья | M11: Сумма
A12: 2 | B12: Февраль | C12: =SUMIFS(Ops!$D:$D,Ops!$G:$G,$B$3,Ops!$H:$H,A12) -> 0 | D12: =SUMIFS(Ops!$E:$E,Ops!$G:$G,$B$3,Ops!$H:$H,A12) -> 0 | E12: =C12-D12 -> 0 | F12: =$B$4+SUM($E$11:E12) -> 1296288.5 | I12: Депозит | J12: 14000000 | L12: Депозит | M12: 4000000
A13: 3 | B13: Март | C13: =SUMIFS(Ops!$D:$D,Ops!$G:$G,$B$3,Ops!$H:$H,A13) -> 0 | D13: =SUMIFS(Ops!$E:$E,Ops!$G:$G,$B$3,Ops!$H:$H,A13) -> 0 | E13: =C13-D13 -> 0 | F13: =$B$4+SUM($E$11:E13) -> 1296288.5 | I13: Оплата от покупателя | J13: 3204561.2 | L13: материалы для производства | M13: 969078.16
A14: 4 | B14: Апрель | C14: =SUMIFS(Ops!$D:$D,Ops!$G:$G,$B$3,Ops!$H:$H,A14) -> 18560380 | D14: =SUMIFS(Ops!$E:$E,Ops!$G:$G,$B$3,Ops!$H:$H,A14) -> 18105118 | E14: =C14-D14 -> 455262.38 | F14: =$B$4+SUM($E$11:E14) -> 1751550.9 | I14: перевод со счета на счет | J14: 682550.18 | L14: перевод со счета на счет | M14: 615013.62
A15: 5 | B15: Май | C15: =SUMIFS(Ops!$D:$D,Ops!$G:$G,$B$3,Ops!$H:$H,A15) -> 61665811 | D15: =SUMIFS(Ops!$E:$E,Ops!$G:$G,$B$3,Ops!$H:$H,A15) -> 62960489 | E15: =C15-D15 -> -1294678.1 | F15: =$B$4+SUM($E$11:E15) -> 456872.77 | I15: Эквайринг | J15: 338668.9 | L15: НДС | M15: 442938
A16: 6 | B16: Июнь | C16: =SUMIFS(Ops!$D:$D,Ops!$G:$G,$B$3,Ops!$H:$H,A16) -> 0 | D16: =SUMIFS(Ops!$E:$E,Ops!$G:$G,$B$3,Ops!$H:$H,A16) -> 0 | E16: =C16-D16 -> 0 | F16: =$B$4+SUM($E$11:E16) -> 456872.77 | I16: Возврат займа контрагентом | J16: 204000 | L16: Перечисление дивидендов | M16: 400000
A17: 7 | B17: Июль | C17: =SUMIFS(Ops!$D:$D,Ops!$G:$G,$B$3,Ops!$H:$H,A17) -> 0 | D17: =SUMIFS(Ops!$E:$E,Ops!$G:$G,$B$3,Ops!$H:$H,A17) -> 0 | E17: =C17-D17 -> 0 | F17: =$B$4+SUM($E$11:E17) -> 456872.77 | I17: Выплата процентов по депозиту | J17: 128206.02 | L17: Товар | M17: 227024.2
A18: 8 | B18: Август | C18: =SUMIFS(Ops!$D:$D,Ops!$G:$G,$B$3,Ops!$H:$H,A18) -> 0 | D18: =SUMIFS(Ops!$E:$E,Ops!$G:$G,$B$3,Ops!$H:$H,A18) -> 0 | E18: =C18-D18 -> 0 | F18: =$B$4+SUM($E$11:E18) -> 456872.77 | I18: Прочее поступление | J18: 2180 | L18: Налоги на персонал | M18: 149194
A19: 9 | B19: Сентябрь | C19: =SUMIFS(Ops!$D:$D,Ops!$G:$G,$B$3,Ops!$H:$H,A19) -> 0 | D19: =SUMIFS(Ops!$E:$E,Ops!$G:$G,$B$3,Ops!$H:$H,A19) -> 0 | E19: =C19-D19 -> 0 | F19: =$B$4+SUM($E$11:E19) -> 456872.77 | I19: Возврат от поставщика | J19: 214 | L19: упаковка | M19: 123002
A20: 10 | B20: Октябрь | C20: =SUMIFS(Ops!$D:$D,Ops!$G:$G,$B$3,Ops!$H:$H,A20) -> 0 | D20: =SUMIFS(Ops!$E:$E,Ops!$G:$G,$B$3,Ops!$H:$H,A20) -> 0 | E20: =C20-D20 -> 0 | F20: =$B$4+SUM($E$11:E20) -> 456872.77 | L20: Возврат кредита банку | M20: 117530.76
A21: 11 | B21: Ноябрь | C21: =SUMIFS(Ops!$D:$D,Ops!$G:$G,$B$3,Ops!$H:$H,A21) -> 0 | D21: =SUMIFS(Ops!$E:$E,Ops!$G:$G,$B$3,Ops!$H:$H,A21) -> 0 | E21: =C21-D21 -> 0 | F21: =$B$4+SUM($E$11:E21) -> 456872.77 | L21: Товар, материал медаль шоколадная | M21: 98000
A22: 12 | B22: Декабрь | C22: =SUMIFS(Ops!$D:$D,Ops!$G:$G,$B$3,Ops!$H:$H,A22) -> 0 | D22: =SUMIFS(Ops!$E:$E,Ops!$G:$G,$B$3,Ops!$H:$H,A22) -> 0 | E22: =C22-D22 -> 0 | F22: =$B$4+SUM($E$11:E22) -> 456872.77
B23: Итого | C23: =SUM(C11:C22) -> 80226191 | D23: =SUM(D11:D22) -> 81065607 | E23: =SUM(E11:E22) -> -839415.71 | F23: =F22 -> 456872.77
A26: Новые операции добавляйте на листе 'Операции' под таблицей. Дата должна быть датой Excel. Если дашборд не обновился сразу, нажмите Ctrl+Alt+F9.
